<?xml version="1.0" encoding="UTF-8"?>
<start name="&lt;start&gt;" pathCondition="true" pathConditionChanged="false">
   <methodCall name="WhileWithMethodCallAsCondition.size(array);" pathCondition="true" pathConditionChanged="false">
      <statement name="int result = 0;" pathCondition="true" pathConditionChanged="false">
         <callStackEntry path="/0"/>
         <statement name="int i = 0;" pathCondition="true" pathConditionChanged="false">
            <callStackEntry path="/0"/>
            <loopInvariant name="invariant: i &gt;= 0 &amp; (i &lt;= array.length &amp; result_1 = i);
variant: javaSubInt(array.length, i)
mod: false" pathCondition="true" pathConditionChanged="false" initiallyValid="true">
               <callStackEntry path="/0"/>
               <branchCondition name="update-application(parallel-upd(elem-update(i)(i_0),elem-update(result_1)(result_1_0)),\[{method-frame(source=size(int[])@WhileWithMethodCallAsCondition): {
    b_3=goOnNice(array,i);
  }
}\] (and(equals(b_3,TRUE),and(geq(i,Z(0(#))),and(geq(length(array),i),equals(result_1,i))))))" pathCondition="update-application(parallel-upd(elem-update(i)(i_0),elem-update(result_1)(result_1_0)),\[{method-frame(source=size(int[])@WhileWithMethodCallAsCondition): {
    b_3=goOnNice(array,i);
  }
}\] (and(equals(b_3,TRUE),and(geq(i,Z(0(#))),and(geq(length(array),i),equals(result_1,i))))))" pathConditionChanged="true" branchCondition="update-application(parallel-upd(elem-update(i)(i_0),elem-update(result_1)(result_1_0)),\[{method-frame(source=size(int[])@WhileWithMethodCallAsCondition): {
    b_3=goOnNice(array,i);
  }
}\] (and(equals(b_3,TRUE),and(geq(i,Z(0(#))),and(geq(length(array),i),equals(result_1,i))))))" mergedBranchCondition="false" isBranchConditionComputed="true" additionalBranchLabel="Body Preserves Invariant">
                  <callStackEntry path="/0"/>
                  <operationContract name="result_3 = goOnNice(array, i) catch(exc_3)
pre: i &lt; 0 | !array = null &amp; i &gt;= 0
post: (   i &lt; 0
   -&gt;   !exc_3 = null
      &amp; java.lang.Exception::instance(exc_3) = TRUE)
&amp; (   !array = null &amp; i &gt;= 0
   -&gt;     result_3
        = \if (i &lt; array.length)
              \then (TRUE)
              \else (FALSE)
      &amp; exc_3 = null)
mod: \if (true)
         \then (     \if (true)
                         \then (     \if (true)
                                         \then (allLocs)
                                         \else (allLocs)
                                \cap \if (  !  array
                                             = null
                                          &amp; i &gt;= 0)
                                         \then (allLocs)
                                         \else (allLocs))
                         \else (allLocs)
                \cap \if (!array = null &amp; i &gt;= 0)
                         \then (allLocs)
                         \else (allLocs))
         \else (allLocs)
\cap \if (!array = null &amp; i &gt;= 0)
         \then (allLocs)
         \else (allLocs)
termination: diamond" pathCondition="update-application(parallel-upd(elem-update(i)(i_0),elem-update(result_1)(result_1_0)),\[{method-frame(source=size(int[])@WhileWithMethodCallAsCondition): {
    b_3=goOnNice(array,i);
  }
}\] (and(equals(b_3,TRUE),and(geq(i,Z(0(#))),and(geq(length(array),i),equals(result_1,i))))))" pathConditionChanged="false" resultTerm="result_3" exceptionTerm="exc_3" contractParameters="array, i" preconditionComplied="true" hasNotNullCheck="false" notNullCheckComplied="false">
                     <callStackEntry path="/0"/>
                     <statement name="result_1++;" pathCondition="update-application(parallel-upd(elem-update(i)(i_0),elem-update(result_1)(result_1_0)),\[{method-frame(source=size(int[])@WhileWithMethodCallAsCondition): {
    b_3=goOnNice(array,i);
  }
}\] (and(equals(b_3,TRUE),and(geq(i,Z(0(#))),and(geq(length(array),i),equals(result_1,i))))))" pathConditionChanged="false">
                        <callStackEntry path="/0"/>
                        <statement name="i++;" pathCondition="update-application(parallel-upd(elem-update(i)(i_0),elem-update(result_1)(result_1_0)),\[{method-frame(source=size(int[])@WhileWithMethodCallAsCondition): {
    b_3=goOnNice(array,i);
  }
}\] (and(equals(b_3,TRUE),and(geq(i,Z(0(#))),and(geq(length(array),i),equals(result_1,i))))))" pathConditionChanged="false">
                           <callStackEntry path="/0"/>
                           <termination name="&lt;loop body end&gt;" pathCondition="update-application(parallel-upd(elem-update(i)(i_0),elem-update(result_1)(result_1_0)),\[{method-frame(source=size(int[])@WhileWithMethodCallAsCondition): {
    b_3=goOnNice(array,i);
  }
}\] (and(equals(b_3,TRUE),and(geq(i,Z(0(#))),and(geq(length(array),i),equals(result_1,i))))))" pathConditionChanged="false" terminationKind="LOOP_BODY" branchVerified="false">
                           </termination>
                        </statement>
                     </statement>
                  </operationContract>
               </branchCondition>
               <branchCondition name="update-application(parallel-upd(elem-update(i)(i_0),elem-update(result_1)(result_1_0)),\&lt;{method-frame(source=size(int[])@WhileWithMethodCallAsCondition): {
    b_3=goOnNice(array,i);
  }
}\&gt; (and(not(equals(b_3,TRUE)),and(geq(i,Z(0(#))),and(geq(length(array),i),equals(result_1,i))))))" pathCondition="update-application(parallel-upd(elem-update(i)(i_0),elem-update(result_1)(result_1_0)),\&lt;{method-frame(source=size(int[])@WhileWithMethodCallAsCondition): {
    b_3=goOnNice(array,i);
  }
}\&gt; (and(not(equals(b_3,TRUE)),and(geq(i,Z(0(#))),and(geq(length(array),i),equals(result_1,i))))))" pathConditionChanged="true" branchCondition="update-application(parallel-upd(elem-update(i)(i_0),elem-update(result_1)(result_1_0)),\&lt;{method-frame(source=size(int[])@WhileWithMethodCallAsCondition): {
    b_3=goOnNice(array,i);
  }
}\&gt; (and(not(equals(b_3,TRUE)),and(geq(i,Z(0(#))),and(geq(length(array),i),equals(result_1,i))))))" mergedBranchCondition="false" isBranchConditionComputed="true" additionalBranchLabel="Use Case">
                  <callStackEntry path="/0"/>
                  <statement name="return result_1;" pathCondition="update-application(parallel-upd(elem-update(i)(i_0),elem-update(result_1)(result_1_0)),\&lt;{method-frame(source=size(int[])@WhileWithMethodCallAsCondition): {
    b_3=goOnNice(array,i);
  }
}\&gt; (and(not(equals(b_3,TRUE)),and(geq(i,Z(0(#))),and(geq(length(array),i),equals(result_1,i))))))" pathConditionChanged="false">
                     <callStackEntry path="/0"/>
                     <methodReturn name="&lt;return of size&gt;" signature="&lt;return of WhileWithMethodCallAsCondition.size(array);&gt;" pathCondition="update-application(parallel-upd(elem-update(i)(i_0),elem-update(result_1)(result_1_0)),\&lt;{method-frame(source=size(int[])@WhileWithMethodCallAsCondition): {
    b_3=goOnNice(array,i);
  }
}\&gt; (and(not(equals(b_3,TRUE)),and(geq(i,Z(0(#))),and(geq(length(array),i),equals(result_1,i))))))" pathConditionChanged="false" isReturnValueComputed="false" methodReturnCondition="update-application(parallel-upd(elem-update(i)(i_0),elem-update(result_1)(result_1_0)),\&lt;{method-frame(source=size(int[])@WhileWithMethodCallAsCondition): {
    b_3=goOnNice(array,i);
  }
}\&gt; (and(not(equals(b_3,TRUE)),and(geq(i,Z(0(#))),and(geq(length(array),i),equals(result_1,i))))))">
                        <callStackEntry path="/0"/>
                        <termination name="&lt;end&gt;" pathCondition="update-application(parallel-upd(elem-update(i)(i_0),elem-update(result_1)(result_1_0)),\&lt;{method-frame(source=size(int[])@WhileWithMethodCallAsCondition): {
    b_3=goOnNice(array,i);
  }
}\&gt; (and(not(equals(b_3,TRUE)),and(geq(i,Z(0(#))),and(geq(length(array),i),equals(result_1,i))))))" pathConditionChanged="false" terminationKind="NORMAL" branchVerified="true">
                        </termination>
                     </methodReturn>
                  </statement>
               </branchCondition>
            </loopInvariant>
         </statement>
      </statement>
      <methodReturnEntry path="/0/0/0/0/1/0/0"/>
   </methodCall>
   <terminationEntry path="/0/0/0/0/0/0/0/0/0"/>
   <terminationEntry path="/0/0/0/0/1/0/0/0"/>
</start>
