<?xml version="1.0" encoding="UTF-8"?>
<start name="&lt;start&gt;" pathCondition="true" pathConditionChanged="false">
   <methodCall name="SimpleObjectQuery.main(x);" pathCondition="true" pathConditionChanged="false">
      <statement name="int magicValue = magic(x);" pathCondition="true" pathConditionChanged="false">
         <operationContract name="result_0 = magic(x) catch(exc_0)
pre: &lt;$inv&gt; &amp; !x = null
post: result_0 = subMagic(x) &amp; &lt;$inv&gt; &amp; exc_0 = null
mod: empty
termination: diamond" pathCondition="true" pathConditionChanged="false" preconditionComplied="false" hasNotNullCheck="false" notNullCheckComplied="false">
            <branchCondition name="true" pathCondition="true" pathConditionChanged="true" branchCondition="true" mergedBranchCondition="false" isBranchConditionComputed="true" additionalBranchLabel="Post (magic)">
               <statement name="return magicValue;" pathCondition="true" pathConditionChanged="false">
                  <methodReturn name="&lt;return of main&gt;" signature="&lt;return of SimpleObjectQuery.main(x);&gt;" pathCondition="true" pathConditionChanged="false" nameIncludingReturnValue="&lt;return 
	res_subMagic_0 {equals(x,null)}, 
	Z(2(4(#))) {and(not(equals(x,null)),equals(java.lang.Object::select(heap,null,SimpleObjectQuery::$INSTANCE),x))}, 
	Z(neglit(1(1(7(4(#)))))) {and(not(equals(x,null)),not(equals(java.lang.Object::select(heap,null,SimpleObjectQuery::$INSTANCE),x)))}
as result of main&gt;" signatureIncludingReturnValue="&lt;return 
	res_subMagic_0 {equals(x,null)}, 
	Z(2(4(#))) {and(not(equals(x,null)),equals(java.lang.Object::select(heap,null,SimpleObjectQuery::$INSTANCE),x))}, 
	Z(neglit(1(1(7(4(#)))))) {and(not(equals(x,null)),not(equals(java.lang.Object::select(heap,null,SimpleObjectQuery::$INSTANCE),x)))}
as result of SimpleObjectQuery.main(x);&gt;" isReturnValueComputed="true" methodReturnCondition="true">
                     <methodReturnValue name="res_subMagic_0 {equals(x,null)}" returnValueString="res_subMagic_0" hasCondition="true" conditionString="equals(x,null)">
                     </methodReturnValue>
                     <methodReturnValue name="Z(2(4(#))) {and(not(equals(x,null)),equals(java.lang.Object::select(heap,null,SimpleObjectQuery::$INSTANCE),x))}" returnValueString="Z(2(4(#)))" hasCondition="true" conditionString="and(not(equals(x,null)),equals(java.lang.Object::select(heap,null,SimpleObjectQuery::$INSTANCE),x))">
                     </methodReturnValue>
                     <methodReturnValue name="Z(neglit(1(1(7(4(#)))))) {and(not(equals(x,null)),not(equals(java.lang.Object::select(heap,null,SimpleObjectQuery::$INSTANCE),x)))}" returnValueString="Z(neglit(1(1(7(4(#))))))" hasCondition="true" conditionString="and(not(equals(x,null)),not(equals(java.lang.Object::select(heap,null,SimpleObjectQuery::$INSTANCE),x)))">
                     </methodReturnValue>
                     <termination name="&lt;end&gt;" pathCondition="true" pathConditionChanged="false" terminationKind="NORMAL" branchVerified="true">
                     </termination>
                  </methodReturn>
               </statement>
            </branchCondition>
         </operationContract>
      </statement>
      <methodReturnEntry path="/0/0/0/0/0/0"/>
   </methodCall>
</start>
